aset2pairs/__init__.py
aset2pairs/aset2pairs.py
aset2pairs-0.1.0.dist-info/LICENSE
aset2pairs-0.1.0.dist-info/WHEEL
aset2pairs-0.1.0.dist-info/METADATA
aset2pairs-0.1.0.dist-info/RECORD
